xk/ChangYing.py
xk/__init__.py
xk/sqlite.py
zhaoyuankang-25.3.26.10.38.dist-info/licenses/LICENSE
zhaoyuankang-25.3.26.10.38.dist-info/METADATA
zhaoyuankang-25.3.26.10.38.dist-info/WHEEL
zhaoyuankang-25.3.26.10.38.dist-info/top_level.txt
zhaoyuankang-25.3.26.10.38.dist-info/RECORD
