Metadata-Version: 2.4
Name: zhaoyuankang
Version: 25.3.26.10.38
Summary: 一个简单的 Python 库
Author-email: ZhaoYuanKang <1756972525@qq.com>
License: MIT License
Project-URL: Personal website, http://121.37.247.246:200/
Requires-Python: >=3.7
License-File: LICENSE
Dynamic: license-file
